[
    {
        "nickname": "LovelyWei",
        "avatar": "https://hex.moe/img/avatar.jpg",
        "site": "https://hex.moe"
    },
    {
        "nickname": "Esonhugh",
        "avatar": "https://eson.ninja/img/reol.png",
        "site": "https://eson.ninja"
    },
    {
        "nickname": "白羊李志远",
        "avatar": "https://nekomoe.xyz/favicon.ico",
        "site": "https://nekomoe.xyz"
    },
    {
        "nickname": "某魏",
        "avatar": "https://secure.gravatar.com/avatar/859eeceaffeec164557ca25d20973d9b?s=512",
        "site": "https://tqlwsl.moe"
    },
    {
        "nickname": "Ulysses Zhan",
        "avatar": "https://avatars.githubusercontent.com/u/26196187?s=512",
        "site": "https://ulysseszh.github.io"
    },
    {
        "nickname": "Thinking Null",
        "avatar": "https://awsl.blog/logo.png",
        "site": "https://awsl.blog"
    },
    {
        "nickname": "桜庭清夏",
        "avatar": "https://cdn.jsdelivr.net/gh/SakurabaKiyoka/lib/img/favicon.png",
        "site": "https://sakurabakiyoka.com"
    },
    {
        "nickname": "ame",
        "avatar": "https://secure.gravatar.com/avatar/97a905669c3f057d3cac4d6912b2ddaf?s=512",
        "site": "https://blog.abyss.moe"
    },
    {
        "nickname": "WeepingDogel",
        "avatar": "https://avatars.githubusercontent.com/u/44858874?s=512",
        "site": "https://weepingdogel.github.io"
    },
    {
        "nickname": "Lss233",
        "avatar": "https://secure.gravatar.com/avatar/2b13911217bbca038c77bfd74e3912d4?s=512",
        "site": "https://blog.lss233.com"
    },
    {
        "nickname": "日下部 詩",
        "avatar": "https://secure.gravatar.com/avatar/499714e709d50be59d690d0b7231f855?s=512",
        "site": "https://www.kskb.eu.org"
    },
    {
        "nickname": "Reliena",
        "avatar": "https://secure.gravatar.com/avatar/6765191a1ca4490345e4bf19b78003a3?s=512",
        "site": "https://blog.cyanoxygen.xyz"
    },
    {
        "nickname": "派兹",
        "avatar": "https://secure.gravatar.com/avatar/9e0030fda7b6e9001ee956911f096fd2?s=512",
        "site": "https://blog.blw.moe"
    },
    {
        "nickname": "萌奈",
        "avatar": "https://cdn.moemona.com/wp-content/uploads/2020/06/80948140_p0.jpg",
        "site": "https://www.moemona.com"
    },
    {
        "nickname": "Piggy",
        "avatar": "https://secure.gravatar.com/avatar/ef920f36f362cb19763b307adfd3d515?s=512",
        "site": "https://blog.piggy.moe"
    },
    {
        "nickname": "Restent Ou",
        "avatar": "https://cdn.jsdelivr.net/gh/Restent/Restent@master/avatar.jpg",
        "site": "https://blog.restent.win"
    },
    {
        "nickname": "Nyarime",
        "avatar": "https://secure.gravatar.com/avatar/2fe9b0ae4ac26dcab28d534e43774b2a?s=512",
        "site": "https://idc.moe"
    },
    {
        "nickname": "kathleen233",
        "avatar": "https://secure.gravatar.com/avatar/c6c42053ceb2a5baed5c66deb6daf615?s=512",
        "site": "https://kathleen233.xyz"
    },
    {
        "nickname": "SkipM4",
        "avatar": "https://secure.gravatar.com/avatar/14eaeed4e2084a06a741f86806234729?s=512",
        "site": "https://skipm4.com"
    },
    {
        "nickname": "sfc9982",
        "avatar": "https://avatars.githubusercontent.com/u/26681591?s=512",
        "site": "https://googles.plus"
    },
    {
        "nickname": "mzwing",
        "avatar": "https://avatars.githubusercontent.com/u/69132261?s=512",
        "site": "https://mzwing.eu.org"
    },
    {
        "nickname": "aisuneko",
        "avatar": "https://aisuneko.pages.dev/images/avatar.webp",
        "site": "https://aisuneko.pages.dev"
    },
    {
        "nickname": "Zenithal",
        "avatar": "https://avatars.githubusercontent.com/u/19512674?s=512",
        "site": "https://blog.zenithal.me"
    },
    {
        "nickname": "Sharzy",
        "avatar": "https://avatars.githubusercontent.com/u/46294732?s=512",
        "site": "https://sharzy.in/blog"
    },
    {
        "nickname": "MiaoTony",
        "avatar": "https://cdn.jsdelivr.net/gh/miaotony/miaotony.github.io/medias/avatar.jpg",
        "site": "https://miaotony.xyz"
    },
    {
        "nickname": "⑨BIE",
        "avatar": "https://avatars.githubusercontent.com/u/12439321?s=512",
        "site": "https://9bie.org"
    },
    {
        "nickname": "131",
        "avatar": "https://cdn.jsdelivr.net/gh/netrvin/netrvin.github.io/blog_resources/3153325051.jpg",
        "site": "https://blog.yuzu.im"
    },
    {
        "nickname": "Edison Jwa",
        "avatar": "https://avatars.githubusercontent.com/u/22003734?s=512",
        "site": "https://www.wevg.org"
    },
    {
        "nickname": "Lexsion",
        "avatar": "https://lexsion.com/usr/themes/R-Blog/img/LexsionFavicon.png",
        "site": "https://lexsion.com"
    },
    {
        "nickname": "零件",
        "avatar": "https://secure.gravatar.com/avatar/dfd75de244e05c7efc2c549670f8c212?s=512",
        "site": "https://nekosc.com"
    },
    {
        "nickname": "477",
        "avatar": "https://secure.gravatar.com/avatar/b222c8aeac939a8a07b831de3b63ea5a?s=512",
        "site": "https://blog.cn47mp.moe"
    },
    {
        "nickname": "Jimmy Tian",
        "avatar": "https://secure.gravatar.com/avatar/0b7a4c2253965e346881bf944d17781f?s=512",
        "site": "https://www.jimmytian.com"
    },
    {
        "nickname": "初雪",
        "avatar": "https://secure.gravatar.com/avatar/3b2ef144e46e1eba6d7e124e4d1929e9?s=512",
        "site": "https://yuki.yuki233.com"
    },
    {
        "nickname": "Sukka",
        "avatar": "https://secure.gravatar.com/avatar/979869bac8c7bd23fbd649064eabd48e?s=512",
        "site": "https://blog.skk.moe"
    },
    {
        "nickname": "DIYgod",
        "avatar": "https://secure.gravatar.com/avatar/6134ff88bd323bc3b1ca888728f134da?s=512",
        "site": "https://diygod.me"
    },
    {
        "nickname": "yiheng",
        "avatar": "https://secure.gravatar.com/avatar/374e36d02476e5b018738aa0df1e726f?s=512",
        "site": "https://blog.yiheng.moe"
    },
    {
        "nickname": "Milkice",
        "avatar": "https://secure.gravatar.com/avatar/832949d1d6427ee587aad01448032da4?s=512",
        "site": "https://milkice.me"
    },
    {
        "nickname": "YuutaW",
        "avatar": "https://secure.gravatar.com/avatar/8ac8a485dd4b0406e2f81b36bf36eecf?s=512",
        "site": "https://blog.yuuta.moe"
    },
    {
        "nickname": "billchenchina",
        "avatar": "https://secure.gravatar.com/avatar/1541e0db587328514c8a2d34de5c5519?s=512",
        "site": "https://billchen.bid"
    },
    {
        "nickname": "Moeka",
        "avatar": "https://secure.gravatar.com/avatar/6ac0a43b024c62a26db1b33f54204eec?s=512",
        "site": "https://moeclue.com"
    },
    {
        "nickname": "EdenJohnson",
        "avatar": "https://pic.edenjohnson.cyou/images/20200625174516.png",
        "site": "https://blog.edenjohnson.cyou"
    },
    {
        "nickname": "猫村 あおい",
        "avatar": "https://nekoquq.github.io/images/static/photo_2019-10-01_13-00-13.jpg",
        "site": "https://nekoquq.github.io"
    }
]
